{
  "db_name": "PostgreSQL",
  "query": "SELECT t1.*, t1.type as transaction_type, t2.exponent from user_transactions t1 left join supported_currencies t2 on t1.currency = t2.currency where transaction_id = $1 and user_address = $2",
  "describe": {
    "columns": [
      {
        "ordinal": 0,
        "name": "id",
        "type_info": "Int4"
      },
      {
        "ordinal": 1,
        "name": "user_address",
        "type_info": "Varchar"
      },
      {
        "ordinal": 2,
        "name": "transaction_id",
        "type_info": "Varchar"
      },
      {
        "ordinal": 3,
        "name": "from_address",
        "type_info": "Varchar"
      },
      {
        "ordinal": 4,
        "name": "to_address",
        "type_info": "Varchar"
      },
      {
        "ordinal": 5,
        "name": "amount",
        "type_info": "Varchar"
      },
      {
        "ordinal": 6,
        "name": "currency",
        "type_info": "Varchar"
      },
      {
        "ordinal": 7,
        "name": "type",
        "type_info": "Varchar"
      },
      {
        "ordinal": 8,
        "name": "status",
        "type_info": "Varchar"
      },
      {
        "ordinal": 9,
        "name": "metadata",
        "type_info": "Jsonb"
      },
      {
        "ordinal": 10,
        "name": "created_at",
        "type_info": "Timestamp"
      },
      {
        "ordinal": 11,
        "name": "updated_at",
        "type_info": "Timestamp"
      },
      {
        "ordinal": 12,
        "name": "transaction_type",
        "type_info": "Varchar"
      },
      {
        "ordinal": 13,
        "name": "exponent",
        "type_info": "Int4"
      }
    ],
    "parameters": {
      "Left": [
        "Text",
        "Text"
      ]
    },
    "nullable": [
      false,
      false,
      false,
      false,
      false,
      false,
      false,
      false,
      false,
      false,
      false,
      false,
      false,
      false
    ]
  },
  "hash": "3ed0a47bd5b6a7bfbe18d73ae3783c86c79043dc7bc282e62abb7d6b463b3fd5"
}
